MANIFEST.in
setup.py
SNBLToolBox/__init__.py
SNBLToolBox/convert.py
SNBLToolBox/frozen.py
SNBLToolBox/mtreewidget.py
SNBLToolBox/wcrysis.py
SNBLToolBox/wdarth.py
SNBLToolBox/wheader.py
SNBLToolBox/wsleuth.py
SNBLToolBox/wsnbltb.py
SNBLToolBox/roerik/__init__.py
SNBLToolBox/roerik/neighbors.py
SNBLToolBox/roerik/wgunnar.py
SNBLToolBox/ui/__init__.py
SNBLToolBox/ui/resources_rc.py
SNBLToolBox/ui/ui_snbltb.py
SNBLToolBox/ui/ui_wcrysis.py
SNBLToolBox/ui/ui_wdarth.py
SNBLToolBox/ui/ui_wgunnar.py
SNBLToolBox/ui/ui_wheader.py
SNBLToolBox/ui/ui_wsleuth.py
SNBLToolBox/ui/ui_wsnbltbabout.py
snbl_toolbox.egg-info/PKG-INFO
snbl_toolbox.egg-info/SOURCES.txt
snbl_toolbox.egg-info/dependency_links.txt
snbl_toolbox.egg-info/entry_points.txt
snbl_toolbox.egg-info/requires.txt
snbl_toolbox.egg-info/top_level.txt