Metadata-Version: 1.1
Name: snbl-toolbox
Version: 2018.1.16
Summary: SNBL Toolbox
Home-page: https://soft.snbl.eu/toolbox.html
Author: Vadim Dyadkin
Author-email: dyadkin@gmail.com
License: GPLv3
Platform: UNKNOWN
Classifier: License :: OSI Approved :: GNU General Public License v3 (GPLv3)
Classifier: Programming Language :: Python
Classifier: Programming Language :: Python :: 3.6
Classifier: Programming Language :: Python :: Implementation :: CPython
